acorgdb/__init__.py
acorgdb/acorgdb.py
acorgdb/test_acorgdb.py
acorgdb-0.1.2.dist-info/METADATA
acorgdb-0.1.2.dist-info/WHEEL
acorgdb-0.1.2.dist-info/top_level.txt
acorgdb-0.1.2.dist-info/RECORD
