Metadata-Version: 2.4
Name: acorgdb
Version: 0.1.2
Summary: Tools for interacting with acorg antigen, antisera and titration databases.
Author-email: David Pattinson <david.pattinson@wisc.edu>
Maintainer-email: David Pattinson <david.pattinson@wisc.edu>
Project-URL: Home, https://github.com/acorg/acorgdb
Classifier: Development Status :: 4 - Beta
Classifier: Environment :: Console
Classifier: Programming Language :: Python
Requires-Python: >=3.7
Requires-Dist: airium
Requires-Dist: pandas
Requires-Dist: regex
Requires-Dist: pyyaml
Provides-Extra: dev
Requires-Dist: pytest; extra == "dev"
Requires-Dist: pytest-subtests; extra == "dev"
